cproto/__init__.py
cproto/core/__init__.py
cproto/core/cproto.py
cproto/core/websocket.py
cproto/domains/__init__.py
cproto/domains/factory.py
cproto/resources/protocol.json
cproto-0.7.2.dist-info/LICENSE
cproto-0.7.2.dist-info/METADATA
cproto-0.7.2.dist-info/WHEEL
cproto-0.7.2.dist-info/top_level.txt
cproto-0.7.2.dist-info/RECORD
